.gitlab-ci.yml
LICENSE
MANIFEST.in
README.md
requirements.txt
setup.py
table_of_adsorption_sites.pdf
acat/.gitkeep
acat/__init__.py
acat/adsorbate_coverage.py
acat/adsorption_sites.py
acat/labels.py
acat/settings.py
acat/setup.py
acat/utilities.py
acat.egg-info/PKG-INFO
acat.egg-info/SOURCES.txt
acat.egg-info/dependency_links.txt
acat.egg-info/requires.txt
acat.egg-info/top_level.txt
acat/acat/__init__.py
acat/acat/adsorbate_coverage.py
acat/acat/adsorption_sites.py
acat/acat/labels.py
acat/acat/settings.py
acat/acat/utilities.py
acat/acat/build/__init__.py
acat/acat/build/action.py
acat/acat/build/adlayer.py
acat/acat/build/ordering.py
acat/acat/ga/__init__.py
acat/acat/ga/adsorbate_comparators.py
acat/acat/ga/adsorbate_operators.py
acat/acat/ga/graph_comparators.py
acat/acat/ga/group_comparators.py
acat/acat/ga/group_operators.py
acat/acat/ga/multitasking.py
acat/acat/ga/particle_crossovers.py
acat/acat/ga/particle_mutations.py
acat/acat/ga/slab_operators.py
acat/build/.gitkeep
acat/build/__init__.py
acat/build/action.py
acat/build/adlayer.py
acat/build/ordering.py
acat/ga/.gitkeep
acat/ga/__init__.py
acat/ga/adsorbate_comparators.py
acat/ga/adsorbate_operators.py
acat/ga/graph_comparators.py
acat/ga/group_comparators.py
acat/ga/group_operators.py
acat/ga/multitasking.py
acat/ga/particle_crossovers.py
acat/ga/particle_mutations.py
acat/ga/slab_operators.py
acat/kernels/wl_kernel.py
docs/.gitkeep
docs/Makefile
docs/acat_favicon.ico
docs/build.rst
docs/conf.py
docs/ga.rst
docs/index.rst
docs/installation.rst
docs/make.bat
docs/modules.rst
docs/notes.rst
docs/utilities.rst
docs/latex/LICRcyr2utf8.xdy
docs/latex/LICRlatin2utf8.xdy
docs/latex/LatinRules.xdy
docs/latex/Makefile
docs/latex/RandomOrderingGenerator.gif
docs/latex/StochasticPatternGenerator.gif
docs/latex/SymmetricOrderingGenerator.gif
docs/latex/SystematicPatternGenerator.gif
docs/latex/acat.log
docs/latex/acat.tex
docs/latex/add_adsorbate.png
docs/latex/add_adsorbate_to_label.png
docs/latex/add_adsorbate_to_site_1.png
docs/latex/add_adsorbate_to_site_2.png
docs/latex/all_coverage_patterns.png
docs/latex/color_facets.png
