Metadata-Version: 2.4
Name: acat
Version: 2.0.1
Summary: Alloy Catalysis Automated Toolkit
Home-page: https://gitlab.com/asm-dtu/acat
Author: Shuang Han
Author-email: hanshuangshiren@gmail.com
Classifier: Programming Language :: Python :: 3
Classifier: License :: OSI Approved :: GNU Lesser General Public License v3 (LGPLv3)
Classifier: Operating System :: POSIX
Requires-Python: >=3.6
License-File: LICENSE
Requires-Dist: ase
Requires-Dist: networkx>=2.4
Dynamic: author
Dynamic: author-email
Dynamic: classifier
Dynamic: description
Dynamic: description-content-type
Dynamic: home-page
Dynamic: license-file
Dynamic: requires-dist
Dynamic: requires-python
Dynamic: summary
